superhelperhxpro/__init__.py
superhelperhxpro/main.py
superhelperhxpro-1.0.5.dist-info/METADATA
superhelperhxpro-1.0.5.dist-info/WHEEL
superhelperhxpro-1.0.5.dist-info/entry_points.txt
superhelperhxpro-1.0.5.dist-info/top_level.txt
superhelperhxpro-1.0.5.dist-info/RECORD
