Metadata-Version: 2.4
Name: superhelperhxpro
Version: 1.0.5
Summary: An intelligent command-line assistant to organize and manage files effortlessly for developers.
Home-page: https://github.com/Suresh-pyhobbyist/superhelperhxpro
Author: Suresh-pyhobbyist
Classifier: Programming Language :: Python :: 3
Classifier: License :: OSI Approved :: MIT License
Classifier: Operating System :: OS Independent
Requires-Python: >=3.7
Dynamic: author
Dynamic: classifier
Dynamic: description
Dynamic: description-content-type
Dynamic: home-page
Dynamic: requires-python
Dynamic: summary
